django_islands/__init__.py
django_islands/apps.py
django_islands/deletion.py
django_islands/exceptions.py
django_islands/fields.py
django_islands/mixins.py
django_islands/models.py
django_islands/query.py
django_islands/settings.py
django_islands/utils.py
django_islands-0.0.3.dist-info/licenses/LICENSE
django_islands-0.0.3.dist-info/METADATA
django_islands-0.0.3.dist-info/WHEEL
django_islands-0.0.3.dist-info/top_level.txt
django_islands-0.0.3.dist-info/RECORD
